decoguard/__init__.py
decoguard/asserts.py
decoguard/config.py
decoguard/decorators.py
decoguard/errors.py
decoguard/validators.py
decoguard-0.1.1.dist-info/licenses/LICENSE
decoguard-0.1.1.dist-info/METADATA
decoguard-0.1.1.dist-info/WHEEL
decoguard-0.1.1.dist-info/top_level.txt
decoguard-0.1.1.dist-info/RECORD
