Metadata-Version: 2.4
Name: decoguard
Version: 0.1.1
Summary: Lightweight Python library for robustly validating decorated functions, providing a clean, structured way to ensure they comply with defined conditions.
Author: Shacode
License-Expression: AGPL-3.0
Project-URL: Homepage, https://gitlab.com/Shacode/decoguard
Project-URL: Repository, https://gitlab.com/Shacode/decoguard
Project-URL: Documentation, https://decoguard.readthedocs.io/en/latest/
Project-URL: Bug Tracker, https://gitlab.com/Shacode/decoguard/-/issues
Keywords: decorators,validation,meta-decorator,introspection
Classifier: Programming Language :: Python :: 3
Classifier: Operating System :: OS Independent
Requires-Python: >=3.13
License-File: LICENSE
Dynamic: license-file
